<?xml version='1.0' encoding='utf-8'?>
<annotation><folder>images</folder><filename>42_2.png</filename><path>images/42_2.png</path><source><database>Unknown</database></source><size><width>7197</width><height>6465</height><depth>3</depth></size><object><name>Dents or Deformation</name><pose>Unspecified</pose><truncated>0</truncated><difficult>0</difficult><bndbox><xmin>4532</xmin><ymin>3494</ymin><xmax>4723</xmax><ymax>3669</ymax></bndbox></object><object><name>Dents or Deformation</name><pose>Unspecified</pose><truncated>0</truncated><difficult>0</difficult><bndbox><xmin>4805</xmin><ymin>3154</ymin><xmax>5210</xmax><ymax>3451</ymax></bndbox></object><object><name>Dents or Deformation</name><pose>Unspecified</pose><truncated>0</truncated><difficult>0</difficult><bndbox><xmin>4649</xmin><ymin>3420</ymin><xmax>4769</xmax><ymax>3542</ymax></bndbox></object><object><name>Paint Peeling</name><pose>Unspecified</pose><truncated>0</truncated><difficult>0</difficult><bndbox><xmin>2410</xmin><ymin>4586</ymin><xmax>2710</xmax><ymax>4840</ymax></bndbox></object><object><name>Cracks</name><pose>Unspecified</pose><truncated>0</truncated><difficult>0</difficult><bndbox><xmin>5799</xmin><ymin>2920</ymin><xmax>5972</xmax><ymax>3074</ymax></bndbox></object></annotation>