<?xml version='1.0' encoding='utf-8'?>
<annotation><folder>images</folder><filename>96_1.png</filename><path>images/96_1.png</path><source><database>Unknown</database></source><size><width>6001</width><height>4001</height><depth>3</depth></size><object><name>Cracks</name><pose>Unspecified</pose><truncated>0</truncated><difficult>0</difficult><bndbox><xmin>3725</xmin><ymin>2529</ymin><xmax>4407</xmax><ymax>3167</ymax></bndbox></object><object><name>Cracks</name><pose>Unspecified</pose><truncated>0</truncated><difficult>0</difficult><bndbox><xmin>3095</xmin><ymin>1814</ymin><xmax>3770</xmax><ymax>2730</ymax></bndbox></object><object><name>Cracks</name><pose>Unspecified</pose><truncated>0</truncated><difficult>0</difficult><bndbox><xmin>2125</xmin><ymin>988</ymin><xmax>3196</xmax><ymax>2074</ymax></bndbox></object></annotation>