<annotation>
	<folder></folder>
	<filename>VID_20250323_180447-1-_mp4-0197_jpg.rf.2f7319c1269925795c253e54b6874767.jpg</filename>
	<path>VID_20250323_180447-1-_mp4-0197_jpg.rf.2f7319c1269925795c253e54b6874767.jpg</path>
	<source>
		<database>roboflow.com</database>
	</source>
	<size>
		<width>640</width>
		<height>640</height>
		<depth>3</depth>
	</size>
	<segmented>0</segmented>
	<object>
		<name>Dents or Deformation</name>
		<pose>Unspecified</pose>
		<truncated>0</truncated>
		<difficult>0</difficult>
		<occluded>0</occluded>
		<bndbox>
			<xmin>97</xmin>
			<xmax>641</xmax>
			<ymin>1</ymin>
			<ymax>159</ymax>
		</bndbox>
	</object>
	<object>
		<name>Scratches</name>
		<pose>Unspecified</pose>
		<truncated>0</truncated>
		<difficult>0</difficult>
		<occluded>0</occluded>
		<bndbox>
			<xmin>61</xmin>
			<xmax>209</xmax>
			<ymin>177</ymin>
			<ymax>239</ymax>
		</bndbox>
	</object>
	<object>
		<name>Scratches</name>
		<pose>Unspecified</pose>
		<truncated>0</truncated>
		<difficult>0</difficult>
		<occluded>0</occluded>
		<bndbox>
			<xmin>1</xmin>
			<xmax>78</xmax>
			<ymin>301</ymin>
			<ymax>366</ymax>
		</bndbox>
	</object>
	<object>
		<name>Scratches</name>
		<pose>Unspecified</pose>
		<truncated>0</truncated>
		<difficult>0</difficult>
		<occluded>0</occluded>
		<bndbox>
			<xmin>155</xmin>
			<xmax>543</xmax>
			<ymin>306</ymin>
			<ymax>400</ymax>
		</bndbox>
	</object>
	<metadata>
	</metadata>
</annotation>
